PymoNNto/__init__.py
PymoNNto/test_pymoNNto.py
PymoNNto/Exploration/Behavior_UI.py
PymoNNto/Exploration/Execute_UI.py
PymoNNto/Exploration/Overview_UI.py
PymoNNto/Exploration/UI_Base.py
PymoNNto/Exploration/__init__.py
PymoNNto/Exploration/AnalysisModules/Static_Classification.py
PymoNNto/Exploration/AnalysisModules/Weight_Classifier_Base.py
PymoNNto/Exploration/AnalysisModules/Weight_Classifier_Post.py
PymoNNto/Exploration/AnalysisModules/Weight_Classifier_Pre.py
PymoNNto/Exploration/AnalysisModules/__init__.py
PymoNNto/Exploration/Evolution/Breed_And_Selection_Module.py
PymoNNto/Exploration/Evolution/Evolution.py
PymoNNto/Exploration/Evolution/EvolutionPlots.py
PymoNNto/Exploration/Evolution/Evolution_Individual.py
PymoNNto/Exploration/Evolution/Evolution_UI.py
PymoNNto/Exploration/Evolution/Interface_Functions.py
PymoNNto/Exploration/Evolution/PlotQTObjects.py
PymoNNto/Exploration/Evolution/SSH_Functions.py
PymoNNto/Exploration/Evolution/Single_Evolution_UI.py
PymoNNto/Exploration/Evolution/TxtHighlighter.py
PymoNNto/Exploration/Evolution/__init__.py
PymoNNto/Exploration/Evolution/common_UI.py
PymoNNto/Exploration/Evolution/communication.py
PymoNNto/Exploration/Evolution/example_master.py
PymoNNto/Exploration/Evolution/example_slave.py
PymoNNto/Exploration/Evolution/example_slave_2.py
PymoNNto/Exploration/Evolution/genome_exchange_com.py
PymoNNto/Exploration/Evolution/Devices/Evolution_Device.py
PymoNNto/Exploration/Evolution/Devices/Evolution_Device_Multi_Thread.py
PymoNNto/Exploration/Evolution/Devices/Evolution_Device_SSH.py
PymoNNto/Exploration/Evolution/Devices/Evolution_Device_Single_Thread.py
PymoNNto/Exploration/Evolution/Devices/__init__.py
PymoNNto/Exploration/HelperFunctions/IteratorFunctions.py
PymoNNto/Exploration/HelperFunctions/Reconstruction.py
PymoNNto/Exploration/HelperFunctions/Save_Load.py
PymoNNto/Exploration/HelperFunctions/Synapses_And_Weights.py
PymoNNto/Exploration/HelperFunctions/Testing.py
PymoNNto-3.0.6.dist-info/LICENSE
PymoNNto-3.0.6.dist-info/METADATA
PymoNNto-3.0.6.dist-info/WHEEL
PymoNNto-3.0.6.dist-info/entry_points.txt
PymoNNto-3.0.6.dist-info/top_level.txt
PymoNNto-3.0.6.dist-info/RECORD
