Metadata-Version: 2.1
Name: PymoNNto
Version: 3.0.6
Summary: Python Modular Neural Network Toolbox
Home-page: https://github.com/trieschlab/PymoNNto
Author: Marius Vieth
Author-email: mv15go@gmail.com
Classifier: Programming Language :: Python :: 3
Classifier: License :: OSI Approved :: MIT License
Classifier: Operating System :: OS Independent
Requires-Python: >=3.6
License-File: LICENSE
Requires-Dist: numpy
Requires-Dist: PyQt5
Requires-Dist: pyqtgraph
Requires-Dist: matplotlib
Requires-Dist: scipy
Requires-Dist: scikit-learn
Requires-Dist: imageio
Requires-Dist: pillow
Requires-Dist: paramiko
Requires-Dist: scp
Requires-Dist: pandas
